{
  "streamer": {
    "name": "stw222",
    "displayName": "stw222",
    "description": "I'm Stephen, or `stew`, I play games. Aviation & flight sim enthusiast.",
    "socials": {
      "twitch": "https://twitch.tv/stw222",
      "youtube": "https://youtube.com/@stw222",
      "discord": "https://discord.gg/kbRBtjSEeZ"
    }
  },
  "timezone": "America/New_York",
  "streams": [
    {
      "date": "2025-12-22",
      "title": "Minecraft Monday",
      "category": "minecraft",
      "startTime": "19:00",
      "description": "Server info:\nEvolved Survival 1.21.10 (& 1.21.11)",
      "image": ""
    },
    {
      "date": "2025-12-23",
      "title": "Anchorage Center",
      "category": "atc",
      "startTime": "19:00",
      "description": "Tuesday on Anchorage Center",
      "image": ""
    },
    {
      "date": "2025-12-26",
      "title": "Boxing Day Staff up",
      "category": "atc",
      "startTime": "14:30",
      "description": "Indy Center\nhttps://flyindycenter.com/events/e81a8769-b30d-4bf9-ae93-1af7e0bfc11e  \nThere might be a chance of this stream not happening. I'm not sure whats happening the day after Christmas.",
      "image": "https://i.postimg.cc/Y26SbtP9/Staff-Up.png"
    },
    {
      "date": "2025-12-27",
      "title": "no stream",
      "category": "flying",
      "startTime": "19:00",
      "description": "",
      "image": ""
    },
    {
      "date": "2025-12-28",
      "title": "Flights around Hawaii - Mele Kalikimaka - Hawaiian Holiday",
      "category": "flying",
      "startTime": "13:45",
      "description": "Routes TBD, but it will include PHKO. This will be a shorter stream due to a family gathering",
      "image": "https://i.imgur.com/H8SiMVo.jpeg"
    },
    {
      "date": "2025-12-29",
      "title": "Minecraft Monday",
      "category": "minecraft",
      "startTime": "19:00",
      "description": "Evolved Survival 1.21.10 (& 1.21.11)\nplay.evolvedsurvival.org\nhttps://findmcserver.com/server/evolvedsurvival",
      "image": ""
    },
    {
      "date": "2025-12-30",
      "title": "GA Tuesday | KCCR Fly-In",
      "category": "flying",
      "startTime": "19:00",
      "description": "Round robbin: KCCR > KAPC > KSTS > KSAC > KCCR\nhttps://www.thepilotclub.org/dispatch/ga-tuesday-30dec2025\nhttps://forums.vatusa.net/index.php?topic=12246.0",
      "image": "https://i.imgur.com/sh56SDp.png"
    },
    {
      "date": "2025-12-31",
      "title": "Wednesday ATC",
      "category": "atc",
      "startTime": "19:00",
      "description": "Indy Center",
      "image": ""
    },
    {
      "date": "2026-1-1",
      "title": "Indy Center",
      "category": "atc",
      "startTime": "19:00",
      "description": "The best center!",
      "image": ""
    },
    {
      "date": "2026-1-2",
      "title": "New Year, New York",
      "category": "flying",
      "startTime": "19:00",
      "description": "KLGA > KBTV > N51 > KLGA\nhttps://forums.vatusa.net/index.php?topic=12301.0\nThe stream will be a little shorter due to student ATC training.",
      "image": "https://i.imgur.com/sSbkKxp.png"
    },
    {
      "date": "2026-1-3",
      "title": "New Year, Nashville",
      "category": "atc",
      "startTime": "18:50",
      "description": "Indy Center || Exact position: PXV81 - The west half of ZID, FL240 and above\nhttps://forums.vatusa.net/index.php?topic=12297.0\nhttps://flyindycenter.com/events/7e6e609f-536e-4754-9f05-b6fa810bc183\nhttps://memphisartcc.com/events/new-year-nashville-62737",
      "image": "https://i.imgur.com/8oRHxOK.jpeg"
    },
    {
      "date": "2026-1-4",
      "title": "Lego Starwars",
      "category": "other",
      "startTime": "14:00",
      "description": "Lego Starwars: the Complete edition - This time its the PC port since the Xbox version had audio issues. I at least went and beat those missions that were beat when playing the xbox version, so we're not starting from scratch.",
      "image": ""
    },
    {
      "date": "2026-1-5",
      "title": "Minecraft Monday",
      "category": "minecraft",
      "startTime": "19:00",
      "description": "New Modpack, Same channel.\nWe'll be playing a new pack called StoneBlock4 on a public server.\nIP: sb4.moddedmc.net",
      "image": "https://cdn.feed-the-beast.com/blob/5b/5b10fbf6e78546a5a4be81a2d311718cc24d29e4277e747028d787d6fec0be46.webp"
    },
    {
      "date": "2026-1-6",
      "title": "No stream",
      "category": "atc",
      "startTime": "19:00",
      "description": "No stream due to ATC training",
      "image": ""
    },
    {
      "date": "2026-1-7",
      "title": "Indy Center | I-64 staff-up",
      "category": "atc",
      "startTime": "18:50",
      "description": "https://flyindycenter.com/events/3f5a2d01-b7d8-4b5c-ad9d-3fd121b8b3d1",
      "image": ""
    },
    {
      "date": "2026-1-8",
      "title": "Fly-In Thursday | CYYZ",
      "category": "flying",
      "startTime": "19:00",
      "description": "This week's TPC Fly-In Thursday is to Toronto Pearson International Airport (CYYZ)!\nAircraft: Starship\nRoute: KMKE SQUIB VIO CLLEM RRALF3 KPTK ZETTR4 TANKO APDAX NUBER6 CYYZ VFR dct KBUF",
      "image": "https://images.squarespace-cdn.com/content/v1/614689d3918044012d2ac1b4/8babe7e8-9c7d-4a35-8e80-490685c78ac0/8jan2026.png"
    },
    {
      "date": "2026-1-9",
      "title": "Southwest VA",
      "category": "flying",
      "startTime": "19:00",
      "description": "Route: KMSP > KSTL > KDTW > to maybe KMDW",
      "image": ""
    },
    {
      "date": "2026-1-10",
      "title": "UPS VA Fly-in to KSDF | Indy Center",
      "category": "atc",
      "startTime": "16:50",
      "description": "Start time is 2200z or maybe earlier\nUPSVAC is flying into Louisville (KSDF) with an estimated arrival time of 2300z. I will control Indy Center.\nhttps://flyindycenter.com/events/f7a7d47c-7696-49cd-a896-e0a73fb92fc1",
      "image": "https://i.imgur.com/JpqqZ2u.png"
    },
    {
      "date": "2026-1-11",
      "title": "No stream",
      "category": "other",
      "startTime": "14:00",
      "description": "No stream",
      "image": ""
    },
    {
      "date": "2026-1-12",
      "title": "Minecraft Monday",
      "category": "minecraft",
      "startTime": "19:00",
      "description": "StoneBlock4 modpack on a public server.\nIP: sb4.moddedmc.net",
      "image": "https://cdn.feed-the-beast.com/blob/5b/5b10fbf6e78546a5a4be81a2d311718cc24d29e4277e747028d787d6fec0be46.webp"
    },
    {
      "date": "2026-1-13",
      "title": "Indy Center | Pilot Club GA Tuesday",
      "category": "atc",
      "startTime": "18:50",
      "description": "TPC is flying between CRW and ILN in a crossfire style where they meet in the middle and go to the opposite destination.\nI will be staffing the south half of Indy Center.\nhttps://www.thepilotclub.org/dispatch/ga-tuesday-13jan2026\nhttps://flyindycenter.com/events/20a71018-74a5-44d7-9528-9b87308842eb",
      "image": "https://images.squarespace-cdn.com/content/v1/614689d3918044012d2ac1b4/1eea3c8d-8b5a-4e84-a85d-f04ae1ab9536/GAT2_16x9_CROSSFIRE.png"
    },
    {
      "date": "2026-1-14",
      "title": "Indy Center",
      "category": "atc",
      "startTime": "19:00",
      "description": "Nearby event - Winter Capital Handoff: https://forums.vatusa.net/index.php?topic=12305.0",
      "image": ""
    },
    {
      "date": "2026-1-15",
      "title": "TPC Explorer Missions - Regional Pilot",
      "category": "flying",
      "startTime": "19:00",
      "description": "KORD - KMSP - KMCI - KCVG - KORD in a Citation\nhttps://www.thepilotclub.org/blog/tpc-explorer-flight-missions-jan2026",
      "image": "https://images.squarespace-cdn.com/content/v1/614689d3918044012d2ac1b4/5954f353-4b02-4983-97d2-e4f4dbcd4456/Screenshot+2025-12-28+at+13.04.24.png"
    },
    {
      "date": "2026-1-16",
      "title": "Honoring the Dream - Indy Center",
      "category": "atc",
      "startTime": "18:50",
      "description": "Atlanta is Honoring the Dream at KATL\nhttps://flyindycenter.com/events/a8a255c7-8153-451f-84e7-474c36313af3\nhttps://forums.vatusa.net/index.php?topic=12316.0",
      "image": "https://www.ztlartcc.org/storage/event_banners/reduced/1766153670.jpg"
    },
    {
      "date": "2026-1-17",
      "title": "Escape to the Desert",
      "category": "flying",
      "startTime": "19:00",
      "description": "KHND > KVGT > KHND https://tinyurl.com/STW-011726\nhttps://forums.vatusa.net/index.php?topic=12312.0",
      "image": "https://i.imgur.com/FmLgnLQ.jpeg"
    },
    {
      "date": "2026-1-18",
      "title": "Sunday Funday - Anchorage Center",
      "category": "atc",
      "startTime": "14:30",
      "description": "TPC is flying from CYXY to PANC starting 3PM EST / 11AM Alaska time\nhttps://www.thepilotclub.org/dispatch/sunday-funday-18jan2026",
      "image": "https://images.squarespace-cdn.com/content/v1/614689d3918044012d2ac1b4/2320b1d4-d6e7-4424-8f9c-0d85d04eddce/SF_16x9_TCPGP.png"
    },
    {
      "date": "2026-1-19",
      "title": "Minecraft Monday",
      "category": "minecraft",
      "startTime": "19:00",
      "description": "StoneBlock4 modpack on a public server.\nIP: sb4.moddedmc.net",
      "image": "https://cdn.feed-the-beast.com/blob/5b/5b10fbf6e78546a5a4be81a2d311718cc24d29e4277e747028d787d6fec0be46.webp"
    },
    {
      "date": "2026-1-20",
      "title": "Anchorage Center",
      "category": "atc",
      "startTime": "19:00",
      "description": "Tuesday on Anchorage Center",
      "image": ""
    },
    {
      "date": "2026-1-21",
      "title": "Indy Center",
      "category": "atc",
      "startTime": "19:00",
      "description": "Come fly into, out of, or over the top of Indy Center!",
      "image": ""
    },
    {
      "date": "2026-1-22",
      "title": "Fly-In Thursday to KHOU",
      "category": "flying",
      "startTime": "19:00",
      "description": "KMSY > KBPT > KHOU in the Bonanza\nTPC pilots are flying to Houston Hobby\nhttps://www.thepilotclub.org/dispatch/sbr-tpc-fly-in-thursday-22jan2026",
      "image": "https://images.squarespace-cdn.com/content/v1/614689d3918044012d2ac1b4/4cee2da0-5da0-4b14-8dd3-d70ca4b9e8fc/22jan2026.png"
    },
    {
      "date": "2026-1-23",
      "title": "Indy Center",
      "category": "atc",
      "startTime": "19:00",
      "description": "Come fly into, out of, or over the top of Indy Center!",
      "image": "https://i.imgur.com/KcZGWSV.png"
    },
    {
      "date": "2026-1-24",
      "title": "Fly-In and out of KPDX",
      "category": "flying",
      "startTime": "19:00",
      "description": "https://forums.vatusa.net/index.php?topic=12320.0",
      "image": "https://zseartcc.org/public/events/logos/361.png?v=1766271781"
    },
    {
      "date": "2026-1-25",
      "title": "Lego Starwars",
      "category": "other",
      "startTime": "14:00",
      "description": "Lego Starwars: the Complete edition - This time its the PC port since the Xbox version had audio issues. I at least went and beat those missions that were beat when playing the xbox version, so we're not starting from scratch.",
      "image": "https://shared.fastly.steamstatic.com/store_item_assets/steam/apps/32440/header.jpg?t=1604517910"
    },
    {
      "date": "2026-1-26",
      "title": "Minecraft Monday",
      "category": "minecraft",
      "startTime": "19:00",
      "description": "StoneBlock4 modpack on a public server.\nIP: sb4.moddedmc.net",
      "image": "https://cdn.feed-the-beast.com/blob/5b/5b10fbf6e78546a5a4be81a2d311718cc24d29e4277e747028d787d6fec0be46.webp"
    },
    {
      "date": "2026-1-27",
      "title": "TPC GA Tuesday - Texas to Louisiana",
      "category": "flying",
      "startTime": "19:00",
      "description": "CXO to KBPT to KLCH\nhttps://www.thepilotclub.org/dispatch/ga-tuesday-27jan2026",
      "image": "https://images.squarespace-cdn.com/content/v1/614689d3918044012d2ac1b4/1668728347994-0A13NP3Y48Z6V0BEID8E/GAT_promo_2b_16x9.png"
    },
    {
      "date": "2026-1-28",
      "title": "Mountains `til Morning - Indy Center",
      "category": "atc",
      "startTime": "18:50",
      "description": "Position: TBA\nThere is a giveaway for 3 pilot winners from Just Flight, Check the event link for info\nhttps://forums.vatusa.net/index.php?topic=12311.0\nhttps://flyindycenter.com/events/c5d695a7-d5e3-4b76-b71d-9156396c8a90\nTPC is flying in the area: https://www.thepilotclub.org/dispatch/bush-wednesday-28jan2026",
      "image": "https://i.postimg.cc/nL57yknG/Mountains-til-Morning.png"
    },
    {
      "date": "2026-1-29",
      "title": "Lego Starwars",
      "category": "other",
      "startTime": "19:00",
      "description": "Lego Starwars: the Complete edition - This time its the PC port since the Xbox version had audio issues. I at least went and beat those missions that were beat when playing the xbox version, so we're not starting from scratch.",
      "image": "https://shared.fastly.steamstatic.com/store_item_assets/steam/apps/32440/header.jpg?t=1604517910"
    },
    {
      "date": "2026-1-30",
      "title": "Indy Center - Northeast Corridor FNO",
      "category": "ATC",
      "startTime": "18:50",
      "description": "https://forums.vatusa.net/index.php?topic=12318.0\nhttps://flyindycenter.com/events/6ccd7ae9-9fb6-47d8-a696-e7789faa9393",
      "image": "https://atchub.bvartcc.com/eventheaders/17e48fa6e7325bdc8f3aed746140ee25.png"
    },
    {
      "date": "2026-1-31",
      "title": "Anchorage Center - Vintage Cross the Inside Passage",
      "category": "ATC",
      "startTime": "08:00",
      "description": "https://zanartcc.org/events/58\nhttps://docs.google.com/document/d/1VDanw9YUeMy8htpF3T8j7NK6Gt2mpJyDKq7xGrc07r8/edit?usp=sharing",
      "image": "https://pbs.twimg.com/media/G5LnCP0XcAANyU6?format=jpg&name=large"
    },
    {
      "date": "2026-2-1",
      "title": "Lego Starwars",
      "category": "other",
      "startTime": "14:00",
      "description": "Lego Starwars: the Complete edition - This time its the PC port since the Xbox version had audio issues. I at least went and beat those missions that were beat when playing the xbox version, so we're not starting from scratch.",
      "image": "https://shared.fastly.steamstatic.com/store_item_assets/steam/apps/32440/header.jpg?t=1604517910"
    },
    {
      "date": "2026-2-2",
      "title": "Minecraft Monday",
      "category": "minecraft",
      "startTime": "19:00",
      "description": "StoneBlock4 modpack on a public server.\nIP: sb4.moddedmc.net",
      "image": "https://cdn.feed-the-beast.com/blob/5b/5b10fbf6e78546a5a4be81a2d311718cc24d29e4277e747028d787d6fec0be46.webp"
    },
    {
      "date": "2026-2-3",
      "title": "Anchorage Center",
      "category": "atc",
      "startTime": "19:00",
      "description": "Tuesday on Anchorage Center",
      "image": ""
    }
  ],
  "categories": {
    "atc": {
      "color": "9147ff",
      "icon": "radar"
    },
    "flying": {
      "color": "#1db954",
      "icon": "airplane"
    },
    "minecraft": {
      "color": "#00b894",
      "icon": "minecraft"
    },
    "other": {
      "color": "#dfeded",
      "icon": "tooltip-question"
    }
  }
}
